pyvfp/__init__.py
pyvfp/pyvfp.py
pyvfp/bin/vfp_to_json.exe
vfp_to_json_lib-0.0.1.dist-info/METADATA
vfp_to_json_lib-0.0.1.dist-info/WHEEL
vfp_to_json_lib-0.0.1.dist-info/top_level.txt
vfp_to_json_lib-0.0.1.dist-info/RECORD
